barcode/DejaVuSansMono.ttf
barcode/__init__.py
barcode/base.py
barcode/codex.py
barcode/ean.py
barcode/errors.py
barcode/isxn.py
barcode/itf.py
barcode/pybarcode.py
barcode/upc.py
barcode/writer.py
barcode/charsets/__init__.py
barcode/charsets/code128.py
barcode/charsets/code39.py
barcode/charsets/ean.py
barcode/charsets/itf.py
barcode/charsets/upc.py
pyBarcode-0.8b1.dist-info/METADATA
pyBarcode-0.8b1.dist-info/WHEEL
pyBarcode-0.8b1.dist-info/entry_points.txt
pyBarcode-0.8b1.dist-info/top_level.txt
pyBarcode-0.8b1.dist-info/RECORD
