Metadata-Version: 2.1
Name: pyBarcode
Version: 0.8b1
Summary: Create standard barcodes with Python. No external modules needed (optional PIL support included).
Home-page: https://bitbucket.org/whitie/python-barcode/
Author: Thorsten Weimann
Author-email: weimann.th@yahoo.com
License: MIT
Platform: UNKNOWN
Classifier: Development Status :: 5 - Production/Stable
Classifier: Environment :: Console
Classifier: Intended Audience :: Developers
Classifier: License :: OSI Approved :: MIT License
Classifier: Operating System :: OS Independent
Classifier: Programming Language :: Python
Classifier: Topic :: Software Development :: Libraries :: Python Modules
Classifier: Topic :: Multimedia :: Graphics
